markmap_anywidget/__init__.py
markmap_anywidget/static/widget.js
markmap_anywidget/static/widget.js.map
markmap_anywidget-0.1.4.dist-info/WHEEL
markmap_anywidget-0.1.4.dist-info/entry_points.txt
markmap_anywidget-0.1.4.dist-info/METADATA
markmap_anywidget-0.1.4.dist-info/RECORD
