Metadata-Version: 2.3
Name: markmap-anywidget
Version: 0.1.4
Summary: anywidget to make interactive mindmaps from markdown using markmap in interactive computing environments
Author: Daniel Fahey
Author-email: Daniel Fahey <daniel.fahey@proton.me>
License: MIT
Classifier: Development Status :: 4 - Beta
Classifier: Framework :: Jupyter
Classifier: Intended Audience :: Developers
Classifier: Intended Audience :: Science/Research
Classifier: License :: OSI Approved :: MIT License
Classifier: Programming Language :: Python :: 3
Classifier: Programming Language :: Python :: 3.10
Classifier: Programming Language :: Python :: 3.11
Classifier: Programming Language :: Python :: 3.12
Classifier: Programming Language :: Python :: 3.13
Classifier: Topic :: Scientific/Engineering :: Visualization
Classifier: Topic :: Software Development :: Libraries :: Python Modules
Classifier: Topic :: Text Processing :: Markup :: Markdown
Requires-Dist: anywidget>=0.9.18
Requires-Python: >=3.10
Project-URL: Bug Tracker, https://github.com/daniel-fahey/markmap-anywidget/issues
Project-URL: Homepage, https://github.com/daniel-fahey/markmap-anywidget
Project-URL: Repository, https://github.com/daniel-fahey/markmap-anywidget
